MANIFEST.in
README.md
requirements.txt
setup.py
uprofile/__init__.py
uprofile/performance_ana.py
uprofile.egg-info/PKG-INFO
uprofile.egg-info/SOURCES.txt
uprofile.egg-info/dependency_links.txt
uprofile.egg-info/requires.txt
uprofile.egg-info/top_level.txt