Metadata-Version: 2.1
Name: uprofile
Version: 1.0.2
Summary: cprofile with graphviz
Home-page: https://gitlab.leihuo.netease.com/shangyue/uprofile
Author: shangyue
Author-email: shangyue@corp.netease.com
License: MIT
Platform: UNKNOWN
